<annotationInfo>
<annotationInfo>
<item  id="84" filename="../../../../../Dell/Documents/HK2_2526/HW_SW/Project_ck/HLS/sha256.cpp" linenumber="14" name="icmp_ln14" contextFuncName="sha256_transform" moduleName="sha256_transform" rtlName="icmp_ln14_fu_1014_p2" latency="0" BRAM="-1" DSP="-1" FF="0" LUT="11" fileDirectory="D:\Phan_mem\Phan_mem\XilinxVivado\zynq_book\sha_256"&gt;&lt;\/item&gt;
<item  id="86" filename="../../../../../Dell/Documents/HK2_2526/HW_SW/Project_ck/HLS/sha256.cpp" linenumber="14" name="i" contextFuncName="sha256_transform" moduleName="sha256_transform" rtlName="i_fu_1020_p2" latency="0" BRAM="-1" DSP="-1" FF="0" LUT="15" fileDirectory="D:\Phan_mem\Phan_mem\XilinxVivado\zynq_book\sha_256"&gt;&lt;\/item&gt;
<item  id="91" filename="../../../../../Dell/Documents/HK2_2526/HW_SW/Project_ck/HLS/sha256.cpp" linenumber="16" name="trunc_ln321" contextFuncName="sha256_transform" moduleName="sha256_transform" rtlName="W_0_V_fu_1030_p17" latency="0" BRAM="-1" DSP="-1" FF="-1" LUT="-1" fileDirectory="D:\Phan_mem\Phan_mem\XilinxVivado\zynq_book\sha_256"&gt;&lt;\/item&gt;
<item  id="92" filename="../../../../../Dell/Documents/HK2_2526/HW_SW/Project_ck/HLS/sha256.cpp" linenumber="16" name="W_0_V" contextFuncName="sha256_transform" moduleName="sha256_transform" rtlName="sha256_core_mux_1bkb_U1" latency="0" BRAM="-1" DSP="-1" FF="-1" LUT="-1" fileDirectory="D:\Phan_mem\Phan_mem\XilinxVivado\zynq_book\sha_256"&gt;&lt;\/item&gt;
<item  id="230" filename="../../../../../Dell/Documents/HK2_2526/HW_SW/Project_ck/HLS/sha256.cpp" linenumber="18" name="icmp_ln18" contextFuncName="sha256_transform" moduleName="sha256_transform" rtlName="icmp_ln18_fu_1231_p2" latency="0" BRAM="-1" DSP="-1" FF="0" LUT="11" fileDirectory="D:\Phan_mem\Phan_mem\XilinxVivado\zynq_book\sha_256"&gt;&lt;\/item&gt;
<item  id="236" filename="../../../../../Dell/Documents/HK2_2526/HW_SW/Project_ck/HLS/sha256.cpp" linenumber="20" name="trunc_ln20" contextFuncName="sha256_transform" moduleName="sha256_transform" rtlName="trunc_ln20_fu_1237_p1" latency="0" BRAM="-1" DSP="-1" FF="-1" LUT="-1" fileDirectory="D:\Phan_mem\Phan_mem\XilinxVivado\zynq_book\sha_256"&gt;&lt;\/item&gt;
<item  id="348" filename="../../../../../Dell/Documents/HK2_2526/HW_SW/Project_ck/HLS/sha256.cpp" linenumber="5" name="r_V" contextFuncName="rotr" moduleName="sha256_transform" rtlName="r_V_fu_1241_p4" latency="0" BRAM="-1" DSP="-1" FF="-1" LUT="-1" fileDirectory="D:\Phan_mem\Phan_mem\XilinxVivado\zynq_book\sha_256"&gt;&lt;\/item&gt;
<item  id="349" filename="../../../../../Dell/Documents/HK2_2526/HW_SW/Project_ck/HLS/sha256.cpp" linenumber="5" name="trunc_ln1503_6" contextFuncName="rotr" moduleName="sha256_transform" rtlName="trunc_ln1503_6_fu_1251_p1" latency="0" BRAM="-1" DSP="-1" FF="-1" LUT="-1" fileDirectory="D:\Phan_mem\Phan_mem\XilinxVivado\zynq_book\sha_256"&gt;&lt;\/item&gt;
<item  id="350" filename="../../../../../Dell/Documents/HK2_2526/HW_SW/Project_ck/HLS/sha256.cpp" linenumber="5" name="ret_V" contextFuncName="rotr" moduleName="sha256_transform" rtlName="ret_V_fu_1255_p3" latency="0" BRAM="-1" DSP="-1" FF="-1" LUT="-1" fileDirectory="D:\Phan_mem\Phan_mem\XilinxVivado\zynq_book\sha_256"&gt;&lt;\/item&gt;
<item  id="351" filename="../../../../../Dell/Documents/HK2_2526/HW_SW/Project_ck/HLS/sha256.cpp" linenumber="20" name="phi_ln20_1" contextFuncName="sha256_transform" moduleName="sha256_transform" rtlName="sha256_core_mux_6cud_U2" latency="0" BRAM="-1" DSP="-1" FF="-1" LUT="-1" fileDirectory="D:\Phan_mem\Phan_mem\XilinxVivado\zynq_book\sha_256"&gt;&lt;\/item&gt;
<item  id="352" filename="../../../../../Dell/Documents/HK2_2526/HW_SW/Project_ck/HLS/sha256.cpp" linenumber="5" name="r_V_6" contextFuncName="rotr" moduleName="sha256_transform" rtlName="r_V_6_fu_1332_p4" latency="0" BRAM="-1" DSP="-1" FF="-1" LUT="-1" fileDirectory="D:\Phan_mem\Phan_mem\XilinxVivado\zynq_book\sha_256"&gt;&lt;\/item&gt;
<item  id="353" filename="../../../../../Dell/Documents/HK2_2526/HW_SW/Project_ck/HLS/sha256.cpp" linenumber="5" name="trunc_ln1503_7" contextFuncName="rotr" moduleName="sha256_transform" rtlName="trunc_ln1503_7_fu_1342_p1" latency="0" BRAM="-1" DSP="-1" FF="-1" LUT="-1" fileDirectory="D:\Phan_mem\Phan_mem\XilinxVivado\zynq_book\sha_256"&gt;&lt;\/item&gt;
<item  id="354" filename="../../../../../Dell/Documents/HK2_2526/HW_SW/Project_ck/HLS/sha256.cpp" linenumber="5" name="ret_V_17" contextFuncName="rotr" moduleName="sha256_transform" rtlName="ret_V_17_fu_1346_p3" latency="0" BRAM="-1" DSP="-1" FF="-1" LUT="-1" fileDirectory="D:\Phan_mem\Phan_mem\XilinxVivado\zynq_book\sha_256"&gt;&lt;\/item&gt;
<item  id="355" filename="../../../../../Dell/Documents/HK2_2526/HW_SW/Project_ck/HLS/sha256.cpp" linenumber="20" name="phi_ln" contextFuncName="sha256_transform" moduleName="sha256_transform" rtlName="sha256_core_mux_6cud_U3" latency="0" BRAM="-1" DSP="-1" FF="-1" LUT="-1" fileDirectory="D:\Phan_mem\Phan_mem\XilinxVivado\zynq_book\sha_256"&gt;&lt;\/item&gt;
<item  id="356" filename="../../../../../Dell/Documents/HK2_2526/HW_SW/Project_ck/HLS/sha256.cpp" linenumber="20" name="r_V_7" contextFuncName="sha256_transform" moduleName="sha256_transform" rtlName="r_V_7_fu_1423_p4" latency="0" BRAM="-1" DSP="-1" FF="-1" LUT="-1" fileDirectory="D:\Phan_mem\Phan_mem\XilinxVivado\zynq_book\sha_256"&gt;&lt;\/item&gt;
<item  id="357" filename="../../../../../Dell/Documents/HK2_2526/HW_SW/Project_ck/HLS/sha256.cpp" linenumber="20" name="r_V_14" contextFuncName="sha256_transform" moduleName="sha256_transform" rtlName="r_V_14_fu_1433_p1" latency="0" BRAM="-1" DSP="-1" FF="-1" LUT="-1" fileDirectory="D:\Phan_mem\Phan_mem\XilinxVivado\zynq_book\sha_256"&gt;&lt;\/item&gt;
<item  id="358" filename="../../../../../Dell/Documents/HK2_2526/HW_SW/Project_ck/HLS/sha256.cpp" linenumber="20" name="xor_ln1357_7" contextFuncName="sha256_transform" moduleName="sha256_transform" rtlName="xor_ln1357_7_fu_1437_p2" latency="0" BRAM="-1" DSP="-1" FF="0" LUT="32" fileDirectory="D:\Phan_mem\Phan_mem\XilinxVivado\zynq_book\sha_256"&gt;&lt;\/item&gt;
<item  id="359" filename="../../../../../Dell/Documents/HK2_2526/HW_SW/Project_ck/HLS/sha256.cpp" linenumber="20" name="ret_V_18" contextFuncName="sha256_transform" moduleName="sha256_transform" rtlName="ret_V_18_fu_1443_p2" latency="0" BRAM="-1" DSP="-1" FF="0" LUT="32" fileDirectory="D:\Phan_mem\Phan_mem\XilinxVivado\zynq_book\sha_256"&gt;&lt;\/item&gt;
<item  id="360" filename="../../../../../Dell/Documents/HK2_2526/HW_SW/Project_ck/HLS/sha256.cpp" linenumber="21" name="phi_ln1" contextFuncName="sha256_transform" moduleName="sha256_transform" rtlName="sha256_core_mux_6cud_U4" latency="0" BRAM="-1" DSP="-1" FF="-1" LUT="-1" fileDirectory="D:\Phan_mem\Phan_mem\XilinxVivado\zynq_book\sha_256"&gt;&lt;\/item&gt;
<item  id="361" filename="../../../../../Dell/Documents/HK2_2526/HW_SW/Project_ck/HLS/sha256.cpp" linenumber="5" name="r_V_8" contextFuncName="rotr" moduleName="sha256_transform" rtlName="r_V_8_fu_1547_p4" latency="0" BRAM="-1" DSP="-1" FF="-1" LUT="-1" fileDirectory="D:\Phan_mem\Phan_mem\XilinxVivado\zynq_book\sha_256"&gt;&lt;\/item&gt;
<item  id="362" filename="../../../../../Dell/Documents/HK2_2526/HW_SW/Project_ck/HLS/sha256.cpp" linenumber="5" name="trunc_ln1503_8" contextFuncName="rotr" moduleName="sha256_transform" rtlName="trunc_ln1503_8_fu_1557_p1" latency="0" BRAM="-1" DSP="-1" FF="-1" LUT="-1" fileDirectory="D:\Phan_mem\Phan_mem\XilinxVivado\zynq_book\sha_256"&gt;&lt;\/item&gt;
<item  id="363" filename="../../../../../Dell/Documents/HK2_2526/HW_SW/Project_ck/HLS/sha256.cpp" linenumber="5" name="ret_V_19" contextFuncName="rotr" moduleName="sha256_transform" rtlName="ret_V_19_fu_1561_p3" latency="0" BRAM="-1" DSP="-1" FF="-1" LUT="-1" fileDirectory="D:\Phan_mem\Phan_mem\XilinxVivado\zynq_book\sha_256"&gt;&lt;\/item&gt;
<item  id="364" filename="../../../../../Dell/Documents/HK2_2526/HW_SW/Project_ck/HLS/sha256.cpp" linenumber="21" name="phi_ln21_1" contextFuncName="sha256_transform" moduleName="sha256_transform" rtlName="sha256_core_mux_6cud_U5" latency="0" BRAM="-1" DSP="-1" FF="-1" LUT="-1" fileDirectory="D:\Phan_mem\Phan_mem\XilinxVivado\zynq_book\sha_256"&gt;&lt;\/item&gt;
<item  id="365" filename="../../../../../Dell/Documents/HK2_2526/HW_SW/Project_ck/HLS/sha256.cpp" linenumber="5" name="r_V_9" contextFuncName="rotr" moduleName="sha256_transform" rtlName="r_V_9_fu_1667_p4" latency="0" BRAM="-1" DSP="-1" FF="-1" LUT="-1" fileDirectory="D:\Phan_mem\Phan_mem\XilinxVivado\zynq_book\sha_256"&gt;&lt;\/item&gt;
<item  id="366" filename="../../../../../Dell/Documents/HK2_2526/HW_SW/Project_ck/HLS/sha256.cpp" linenumber="5" name="trunc_ln1503_9" contextFuncName="rotr" moduleName="sha256_transform" rtlName="trunc_ln1503_9_fu_1677_p1" latency="0" BRAM="-1" DSP="-1" FF="-1" LUT="-1" fileDirectory="D:\Phan_mem\Phan_mem\XilinxVivado\zynq_book\sha_256"&gt;&lt;\/item&gt;
<item  id="367" filename="../../../../../Dell/Documents/HK2_2526/HW_SW/Project_ck/HLS/sha256.cpp" linenumber="5" name="ret_V_20" contextFuncName="rotr" moduleName="sha256_transform" rtlName="ret_V_20_fu_1681_p3" latency="0" BRAM="-1" DSP="-1" FF="-1" LUT="-1" fileDirectory="D:\Phan_mem\Phan_mem\XilinxVivado\zynq_book\sha_256"&gt;&lt;\/item&gt;
<item  id="368" filename="../../../../../Dell/Documents/HK2_2526/HW_SW/Project_ck/HLS/sha256.cpp" linenumber="21" name="phi_ln1503_1" contextFuncName="sha256_transform" moduleName="sha256_transform" rtlName="sha256_core_mux_6cud_U6" latency="0" BRAM="-1" DSP="-1" FF="-1" LUT="-1" fileDirectory="D:\Phan_mem\Phan_mem\XilinxVivado\zynq_book\sha_256"&gt;&lt;\/item&gt;
<item  id="369" filename="../../../../../Dell/Documents/HK2_2526/HW_SW/Project_ck/HLS/sha256.cpp" linenumber="21" name="r_V_10" contextFuncName="sha256_transform" moduleName="sha256_transform" rtlName="r_V_10_fu_1787_p4" latency="0" BRAM="-1" DSP="-1" FF="-1" LUT="-1" fileDirectory="D:\Phan_mem\Phan_mem\XilinxVivado\zynq_book\sha_256"&gt;&lt;\/item&gt;
<item  id="370" filename="../../../../../Dell/Documents/HK2_2526/HW_SW/Project_ck/HLS/sha256.cpp" linenumber="21" name="r_V_15" contextFuncName="sha256_transform" moduleName="sha256_transform" rtlName="r_V_15_fu_1797_p1" latency="0" BRAM="-1" DSP="-1" FF="-1" LUT="-1" fileDirectory="D:\Phan_mem\Phan_mem\XilinxVivado\zynq_book\sha_256"&gt;&lt;\/item&gt;
<item  id="371" filename="../../../../../Dell/Documents/HK2_2526/HW_SW/Project_ck/HLS/sha256.cpp" linenumber="21" name="xor_ln1357_9" contextFuncName="sha256_transform" moduleName="sha256_transform" rtlName="xor_ln1357_9_fu_1801_p2" latency="0" BRAM="-1" DSP="-1" FF="0" LUT="32" fileDirectory="D:\Phan_mem\Phan_mem\XilinxVivado\zynq_book\sha_256"&gt;&lt;\/item&gt;
<item  id="372" filename="../../../../../Dell/Documents/HK2_2526/HW_SW/Project_ck/HLS/sha256.cpp" linenumber="21" name="ret_V_21" contextFuncName="sha256_transform" moduleName="sha256_transform" rtlName="ret_V_21_fu_1807_p2" latency="0" BRAM="-1" DSP="-1" FF="0" LUT="32" fileDirectory="D:\Phan_mem\Phan_mem\XilinxVivado\zynq_book\sha_256"&gt;&lt;\/item&gt;
<item  id="373" filename="../../../../../Dell/Documents/HK2_2526/HW_SW/Project_ck/HLS/sha256.cpp" linenumber="22" name="phi_ln2" contextFuncName="sha256_transform" moduleName="sha256_transform" rtlName="sha256_core_mux_6cud_U7" latency="0" BRAM="-1" DSP="-1" FF="-1" LUT="-1" fileDirectory="D:\Phan_mem\Phan_mem\XilinxVivado\zynq_book\sha_256"&gt;&lt;\/item&gt;
<item  id="374" filename="../../../../../Dell/Documents/HK2_2526/HW_SW/Project_ck/HLS/sha256.cpp" linenumber="22" name="phi_ln215_1" contextFuncName="sha256_transform" moduleName="sha256_transform" rtlName="sha256_core_mux_6cud_U8" latency="0" BRAM="-1" DSP="-1" FF="-1" LUT="-1" fileDirectory="D:\Phan_mem\Phan_mem\XilinxVivado\zynq_book\sha_256"&gt;&lt;\/item&gt;
<item  id="375" filename="../../../../../Dell/Documents/HK2_2526/HW_SW/Project_ck/HLS/sha256.cpp" linenumber="22" name="add_ln209_7" contextFuncName="sha256_transform" moduleName="sha256_transform" rtlName="add_ln209_7_fu_1976_p2" latency="0" BRAM="-1" DSP="-1" FF="0" LUT="39" fileDirectory="D:\Phan_mem\Phan_mem\XilinxVivado\zynq_book\sha_256"&gt;&lt;\/item&gt;
<item  id="376" filename="../../../../../Dell/Documents/HK2_2526/HW_SW/Project_ck/HLS/sha256.cpp" linenumber="22" name="add_ln209_8" contextFuncName="sha256_transform" moduleName="sha256_transform" rtlName="add_ln209_8_fu_1982_p2" latency="0" BRAM="-1" DSP="-1" FF="0" LUT="32" fileDirectory="D:\Phan_mem\Phan_mem\XilinxVivado\zynq_book\sha_256"&gt;&lt;\/item&gt;
<item  id="377" filename="../../../../../Dell/Documents/HK2_2526/HW_SW/Project_ck/HLS/sha256.cpp" linenumber="22" name="W_16_V" contextFuncName="sha256_transform" moduleName="sha256_transform" rtlName="W_16_V_fu_1988_p2" latency="0" BRAM="-1" DSP="-1" FF="0" LUT="32" fileDirectory="D:\Phan_mem\Phan_mem\XilinxVivado\zynq_book\sha_256"&gt;&lt;\/item&gt;
<item  id="525" filename="../../../../../Dell/Documents/HK2_2526/HW_SW/Project_ck/HLS/sha256.cpp" linenumber="18" name="i_2" contextFuncName="sha256_transform" moduleName="sha256_transform" rtlName="i_2_fu_2234_p2" latency="0" BRAM="-1" DSP="-1" FF="0" LUT="15" fileDirectory="D:\Phan_mem\Phan_mem\XilinxVivado\zynq_book\sha_256"&gt;&lt;\/item&gt;
<item  id="539" filename="../../../../../Dell/Documents/HK2_2526/HW_SW/Project_ck/HLS/sha256.cpp" linenumber="36" name="icmp_ln36" contextFuncName="sha256_transform" moduleName="sha256_transform" rtlName="icmp_ln36_fu_2240_p2" latency="0" BRAM="-1" DSP="-1" FF="0" LUT="11" fileDirectory="D:\Phan_mem\Phan_mem\XilinxVivado\zynq_book\sha_256"&gt;&lt;\/item&gt;
<item  id="541" filename="../../../../../Dell/Documents/HK2_2526/HW_SW/Project_ck/HLS/sha256.cpp" linenumber="36" name="i_1" contextFuncName="sha256_transform" moduleName="sha256_transform" rtlName="i_1_fu_2246_p2" latency="0" BRAM="-1" DSP="-1" FF="0" LUT="15" fileDirectory="D:\Phan_mem\Phan_mem\XilinxVivado\zynq_book\sha_256"&gt;&lt;\/item&gt;
<item  id="563" filename="../../../../../Dell/Documents/HK2_2526/HW_SW/Project_ck/HLS/sha256.cpp" linenumber="5" name="r_V_s" contextFuncName="rotr" moduleName="sha256_transform" rtlName="r_V_s_fu_2258_p4" latency="0" BRAM="-1" DSP="-1" FF="-1" LUT="-1" fileDirectory="D:\Phan_mem\Phan_mem\XilinxVivado\zynq_book\sha_256"&gt;&lt;\/item&gt;
<item  id="564" filename="../../../../../Dell/Documents/HK2_2526/HW_SW/Project_ck/HLS/sha256.cpp" linenumber="5" name="trunc_ln1503" contextFuncName="rotr" moduleName="sha256_transform" rtlName="trunc_ln1503_fu_2268_p1" latency="0" BRAM="-1" DSP="-1" FF="-1" LUT="-1" fileDirectory="D:\Phan_mem\Phan_mem\XilinxVivado\zynq_book\sha_256"&gt;&lt;\/item&gt;
<item  id="565" filename="../../../../../Dell/Documents/HK2_2526/HW_SW/Project_ck/HLS/sha256.cpp" linenumber="5" name="ret_V_22" contextFuncName="rotr" moduleName="sha256_transform" rtlName="ret_V_22_fu_2272_p3" latency="0" BRAM="-1" DSP="-1" FF="-1" LUT="-1" fileDirectory="D:\Phan_mem\Phan_mem\XilinxVivado\zynq_book\sha_256"&gt;&lt;\/item&gt;
<item  id="566" filename="../../../../../Dell/Documents/HK2_2526/HW_SW/Project_ck/HLS/sha256.cpp" linenumber="5" name="r_V_1" contextFuncName="rotr" moduleName="sha256_transform" rtlName="r_V_1_fu_2280_p4" latency="0" BRAM="-1" DSP="-1" FF="-1" LUT="-1" fileDirectory="D:\Phan_mem\Phan_mem\XilinxVivado\zynq_book\sha_256"&gt;&lt;\/item&gt;
<item  id="567" filename="../../../../../Dell/Documents/HK2_2526/HW_SW/Project_ck/HLS/sha256.cpp" linenumber="5" name="trunc_ln1503_1" contextFuncName="rotr" moduleName="sha256_transform" rtlName="trunc_ln1503_1_fu_2290_p1" latency="0" BRAM="-1" DSP="-1" FF="-1" LUT="-1" fileDirectory="D:\Phan_mem\Phan_mem\XilinxVivado\zynq_book\sha_256"&gt;&lt;\/item&gt;
<item  id="568" filename="../../../../../Dell/Documents/HK2_2526/HW_SW/Project_ck/HLS/sha256.cpp" linenumber="5" name="ret_V_23" contextFuncName="rotr" moduleName="sha256_transform" rtlName="ret_V_23_fu_2294_p3" latency="0" BRAM="-1" DSP="-1" FF="-1" LUT="-1" fileDirectory="D:\Phan_mem\Phan_mem\XilinxVivado\zynq_book\sha_256"&gt;&lt;\/item&gt;
<item  id="569" filename="../../../../../Dell/Documents/HK2_2526/HW_SW/Project_ck/HLS/sha256.cpp" linenumber="5" name="r_V_2" contextFuncName="rotr" moduleName="sha256_transform" rtlName="r_V_2_fu_2302_p4" latency="0" BRAM="-1" DSP="-1" FF="-1" LUT="-1" fileDirectory="D:\Phan_mem\Phan_mem\XilinxVivado\zynq_book\sha_256"&gt;&lt;\/item&gt;
<item  id="570" filename="../../../../../Dell/Documents/HK2_2526/HW_SW/Project_ck/HLS/sha256.cpp" linenumber="5" name="trunc_ln1503_2" contextFuncName="rotr" moduleName="sha256_transform" rtlName="trunc_ln1503_2_fu_2312_p1" latency="0" BRAM="-1" DSP="-1" FF="-1" LUT="-1" fileDirectory="D:\Phan_mem\Phan_mem\XilinxVivado\zynq_book\sha_256"&gt;&lt;\/item&gt;
<item  id="571" filename="../../../../../Dell/Documents/HK2_2526/HW_SW/Project_ck/HLS/sha256.cpp" linenumber="5" name="ret_V_24" contextFuncName="rotr" moduleName="sha256_transform" rtlName="ret_V_24_fu_2316_p3" latency="0" BRAM="-1" DSP="-1" FF="-1" LUT="-1" fileDirectory="D:\Phan_mem\Phan_mem\XilinxVivado\zynq_book\sha_256"&gt;&lt;\/item&gt;
<item  id="572" filename="../../../../../Dell/Documents/HK2_2526/HW_SW/Project_ck/HLS/sha256.cpp" linenumber="38" name="xor_ln1357" contextFuncName="sha256_transform" moduleName="sha256_transform" rtlName="xor_ln1357_fu_2324_p2" latency="0" BRAM="-1" DSP="-1" FF="0" LUT="32" fileDirectory="D:\Phan_mem\Phan_mem\XilinxVivado\zynq_book\sha_256"&gt;&lt;\/item&gt;
<item  id="573" filename="../../../../../Dell/Documents/HK2_2526/HW_SW/Project_ck/HLS/sha256.cpp" linenumber="38" name="ret_V_25" contextFuncName="sha256_transform" moduleName="sha256_transform" rtlName="ret_V_25_fu_2330_p2" latency="0" BRAM="-1" DSP="-1" FF="0" LUT="32" fileDirectory="D:\Phan_mem\Phan_mem\XilinxVivado\zynq_book\sha_256"&gt;&lt;\/item&gt;
<item  id="574" filename="../../../../../Dell/Documents/HK2_2526/HW_SW/Project_ck/HLS/sha256.cpp" linenumber="39" name="ret_V_26" contextFuncName="sha256_transform" moduleName="sha256_transform" rtlName="ret_V_26_fu_2336_p2" latency="0" BRAM="-1" DSP="-1" FF="0" LUT="32" fileDirectory="D:\Phan_mem\Phan_mem\XilinxVivado\zynq_book\sha_256"&gt;&lt;\/item&gt;
<item  id="575" filename="../../../../../Dell/Documents/HK2_2526/HW_SW/Project_ck/HLS/sha256.cpp" linenumber="39" name="r_V_16" contextFuncName="sha256_transform" moduleName="sha256_transform" rtlName="r_V_16_fu_2342_p2" latency="0" BRAM="-1" DSP="-1" FF="0" LUT="32" fileDirectory="D:\Phan_mem\Phan_mem\XilinxVivado\zynq_book\sha_256"&gt;&lt;\/item&gt;
<item  id="576" filename="../../../../../Dell/Documents/HK2_2526/HW_SW/Project_ck/HLS/sha256.cpp" linenumber="39" name="ret_V_27" contextFuncName="sha256_transform" moduleName="sha256_transform" rtlName="ret_V_27_fu_2348_p2" latency="0" BRAM="-1" DSP="-1" FF="0" LUT="32" fileDirectory="D:\Phan_mem\Phan_mem\XilinxVivado\zynq_book\sha_256"&gt;&lt;\/item&gt;
<item  id="577" filename="../../../../../Dell/Documents/HK2_2526/HW_SW/Project_ck/HLS/sha256.cpp" linenumber="39" name="ret_V_28" contextFuncName="sha256_transform" moduleName="sha256_transform" rtlName="ret_V_28_fu_2354_p2" latency="0" BRAM="-1" DSP="-1" FF="0" LUT="32" fileDirectory="D:\Phan_mem\Phan_mem\XilinxVivado\zynq_book\sha_256"&gt;&lt;\/item&gt;
<item  id="578" filename="../../../../../Dell/Documents/HK2_2526/HW_SW/Project_ck/HLS/sha256.cpp" linenumber="40" name="zext_ln40" contextFuncName="sha256_transform" moduleName="sha256_transform" rtlName="zext_ln40_fu_2360_p1" latency="0" BRAM="-1" DSP="-1" FF="-1" LUT="-1" fileDirectory="D:\Phan_mem\Phan_mem\XilinxVivado\zynq_book\sha_256"&gt;&lt;\/item&gt;
<item  id="581" filename="../../../../../Dell/Documents/HK2_2526/HW_SW/Project_ck/HLS/sha256.cpp" linenumber="40" name="trunc_ln215" contextFuncName="sha256_transform" moduleName="sha256_transform" rtlName="tmp_1_fu_2369_p65" latency="0" BRAM="-1" DSP="-1" FF="-1" LUT="-1" fileDirectory="D:\Phan_mem\Phan_mem\XilinxVivado\zynq_book\sha_256"&gt;&lt;\/item&gt;
<item  id="582" filename="../../../../../Dell/Documents/HK2_2526/HW_SW/Project_ck/HLS/sha256.cpp" linenumber="40" name="tmp_1" contextFuncName="sha256_transform" moduleName="sha256_transform" rtlName="sha256_core_mux_6cud_U9" latency="0" BRAM="-1" DSP="-1" FF="-1" LUT="-1" fileDirectory="D:\Phan_mem\Phan_mem\XilinxVivado\zynq_book\sha_256"&gt;&lt;\/item&gt;
<item  id="583" filename="../../../../../Dell/Documents/HK2_2526/HW_SW/Project_ck/HLS/sha256.cpp" linenumber="40" name="add_ln209" contextFuncName="sha256_transform" moduleName="sha256_transform" rtlName="add_ln209_fu_2579_p2" latency="0" BRAM="-1" DSP="-1" FF="0" LUT="32" fileDirectory="D:\Phan_mem\Phan_mem\XilinxVivado\zynq_book\sha_256"&gt;&lt;\/item&gt;
<item  id="584" filename="../../../../../Dell/Documents/HK2_2526/HW_SW/Project_ck/HLS/sha256.cpp" linenumber="40" name="add_ln209_1" contextFuncName="sha256_transform" moduleName="sha256_transform" rtlName="add_ln209_1_fu_2455_p2" latency="0" BRAM="-1" DSP="-1" FF="0" LUT="32" fileDirectory="D:\Phan_mem\Phan_mem\XilinxVivado\zynq_book\sha_256"&gt;&lt;\/item&gt;
<item  id="585" filename="../../../../../Dell/Documents/HK2_2526/HW_SW/Project_ck/HLS/sha256.cpp" linenumber="40" name="add_ln209_2" contextFuncName="sha256_transform" moduleName="sha256_transform" rtlName="add_ln209_2_fu_2461_p2" latency="0" BRAM="-1" DSP="-1" FF="0" LUT="32" fileDirectory="D:\Phan_mem\Phan_mem\XilinxVivado\zynq_book\sha_256"&gt;&lt;\/item&gt;
<item  id="586" filename="../../../../../Dell/Documents/HK2_2526/HW_SW/Project_ck/HLS/sha256.cpp" linenumber="40" name="t1_V" contextFuncName="sha256_transform" moduleName="sha256_transform" rtlName="t1_V_fu_2584_p2" latency="0" BRAM="-1" DSP="-1" FF="0" LUT="32" fileDirectory="D:\Phan_mem\Phan_mem\XilinxVivado\zynq_book\sha_256"&gt;&lt;\/item&gt;
<item  id="587" filename="../../../../../Dell/Documents/HK2_2526/HW_SW/Project_ck/HLS/sha256.cpp" linenumber="5" name="r_V_3" contextFuncName="rotr" moduleName="sha256_transform" rtlName="r_V_3_fu_2589_p4" latency="0" BRAM="-1" DSP="-1" FF="-1" LUT="-1" fileDirectory="D:\Phan_mem\Phan_mem\XilinxVivado\zynq_book\sha_256"&gt;&lt;\/item&gt;
<item  id="588" filename="../../../../../Dell/Documents/HK2_2526/HW_SW/Project_ck/HLS/sha256.cpp" linenumber="5" name="trunc_ln1503_3" contextFuncName="rotr" moduleName="sha256_transform" rtlName="trunc_ln1503_3_fu_2599_p1" latency="0" BRAM="-1" DSP="-1" FF="-1" LUT="-1" fileDirectory="D:\Phan_mem\Phan_mem\XilinxVivado\zynq_book\sha_256"&gt;&lt;\/item&gt;
<item  id="589" filename="../../../../../Dell/Documents/HK2_2526/HW_SW/Project_ck/HLS/sha256.cpp" linenumber="5" name="ret_V_29" contextFuncName="rotr" moduleName="sha256_transform" rtlName="ret_V_29_fu_2603_p3" latency="0" BRAM="-1" DSP="-1" FF="-1" LUT="-1" fileDirectory="D:\Phan_mem\Phan_mem\XilinxVivado\zynq_book\sha_256"&gt;&lt;\/item&gt;
<item  id="590" filename="../../../../../Dell/Documents/HK2_2526/HW_SW/Project_ck/HLS/sha256.cpp" linenumber="5" name="r_V_4" contextFuncName="rotr" moduleName="sha256_transform" rtlName="r_V_4_fu_2611_p4" latency="0" BRAM="-1" DSP="-1" FF="-1" LUT="-1" fileDirectory="D:\Phan_mem\Phan_mem\XilinxVivado\zynq_book\sha_256"&gt;&lt;\/item&gt;
<item  id="591" filename="../../../../../Dell/Documents/HK2_2526/HW_SW/Project_ck/HLS/sha256.cpp" linenumber="5" name="trunc_ln1503_4" contextFuncName="rotr" moduleName="sha256_transform" rtlName="trunc_ln1503_4_fu_2621_p1" latency="0" BRAM="-1" DSP="-1" FF="-1" LUT="-1" fileDirectory="D:\Phan_mem\Phan_mem\XilinxVivado\zynq_book\sha_256"&gt;&lt;\/item&gt;
<item  id="592" filename="../../../../../Dell/Documents/HK2_2526/HW_SW/Project_ck/HLS/sha256.cpp" linenumber="5" name="ret_V_30" contextFuncName="rotr" moduleName="sha256_transform" rtlName="ret_V_30_fu_2625_p3" latency="0" BRAM="-1" DSP="-1" FF="-1" LUT="-1" fileDirectory="D:\Phan_mem\Phan_mem\XilinxVivado\zynq_book\sha_256"&gt;&lt;\/item&gt;
<item  id="593" filename="../../../../../Dell/Documents/HK2_2526/HW_SW/Project_ck/HLS/sha256.cpp" linenumber="5" name="r_V_5" contextFuncName="rotr" moduleName="sha256_transform" rtlName="r_V_5_fu_2633_p4" latency="0" BRAM="-1" DSP="-1" FF="-1" LUT="-1" fileDirectory="D:\Phan_mem\Phan_mem\XilinxVivado\zynq_book\sha_256"&gt;&lt;\/item&gt;
<item  id="594" filename="../../../../../Dell/Documents/HK2_2526/HW_SW/Project_ck/HLS/sha256.cpp" linenumber="5" name="trunc_ln1503_5" contextFuncName="rotr" moduleName="sha256_transform" rtlName="trunc_ln1503_5_fu_2643_p1" latency="0" BRAM="-1" DSP="-1" FF="-1" LUT="-1" fileDirectory="D:\Phan_mem\Phan_mem\XilinxVivado\zynq_book\sha_256"&gt;&lt;\/item&gt;
<item  id="595" filename="../../../../../Dell/Documents/HK2_2526/HW_SW/Project_ck/HLS/sha256.cpp" linenumber="5" name="ret_V_31" contextFuncName="rotr" moduleName="sha256_transform" rtlName="ret_V_31_fu_2647_p3" latency="0" BRAM="-1" DSP="-1" FF="-1" LUT="-1" fileDirectory="D:\Phan_mem\Phan_mem\XilinxVivado\zynq_book\sha_256"&gt;&lt;\/item&gt;
<item  id="596" filename="../../../../../Dell/Documents/HK2_2526/HW_SW/Project_ck/HLS/sha256.cpp" linenumber="41" name="xor_ln1357_3" contextFuncName="sha256_transform" moduleName="sha256_transform" rtlName="xor_ln1357_3_fu_2655_p2" latency="0" BRAM="-1" DSP="-1" FF="0" LUT="32" fileDirectory="D:\Phan_mem\Phan_mem\XilinxVivado\zynq_book\sha_256"&gt;&lt;\/item&gt;
<item  id="597" filename="../../../../../Dell/Documents/HK2_2526/HW_SW/Project_ck/HLS/sha256.cpp" linenumber="41" name="ret_V_32" contextFuncName="sha256_transform" moduleName="sha256_transform" rtlName="ret_V_32_fu_2661_p2" latency="0" BRAM="-1" DSP="-1" FF="0" LUT="32" fileDirectory="D:\Phan_mem\Phan_mem\XilinxVivado\zynq_book\sha_256"&gt;&lt;\/item&gt;
<item  id="598" filename="../../../../../Dell/Documents/HK2_2526/HW_SW/Project_ck/HLS/sha256.cpp" linenumber="42" name="xor_ln1357_5" contextFuncName="sha256_transform" moduleName="sha256_transform" rtlName="xor_ln1357_5_fu_2467_p2" latency="0" BRAM="-1" DSP="-1" FF="0" LUT="32" fileDirectory="D:\Phan_mem\Phan_mem\XilinxVivado\zynq_book\sha_256"&gt;&lt;\/item&gt;
<item  id="599" filename="../../../../../Dell/Documents/HK2_2526/HW_SW/Project_ck/HLS/sha256.cpp" linenumber="42" name="ret_V_33" contextFuncName="sha256_transform" moduleName="sha256_transform" rtlName="ret_V_33_fu_2473_p2" latency="0" BRAM="-1" DSP="-1" FF="0" LUT="32" fileDirectory="D:\Phan_mem\Phan_mem\XilinxVivado\zynq_book\sha_256"&gt;&lt;\/item&gt;
<item  id="600" filename="../../../../../Dell/Documents/HK2_2526/HW_SW/Project_ck/HLS/sha256.cpp" linenumber="42" name="ret_V_34" contextFuncName="sha256_transform" moduleName="sha256_transform" rtlName="ret_V_34_fu_2479_p2" latency="0" BRAM="-1" DSP="-1" FF="0" LUT="32" fileDirectory="D:\Phan_mem\Phan_mem\XilinxVivado\zynq_book\sha_256"&gt;&lt;\/item&gt;
<item  id="601" filename="../../../../../Dell/Documents/HK2_2526/HW_SW/Project_ck/HLS/sha256.cpp" linenumber="42" name="ret_V_35" contextFuncName="sha256_transform" moduleName="sha256_transform" rtlName="ret_V_35_fu_2485_p2" latency="0" BRAM="-1" DSP="-1" FF="0" LUT="32" fileDirectory="D:\Phan_mem\Phan_mem\XilinxVivado\zynq_book\sha_256"&gt;&lt;\/item&gt;
<item  id="602" filename="../../../../../Dell/Documents/HK2_2526/HW_SW/Project_ck/HLS/sha256.cpp" linenumber="44" name="e_V" contextFuncName="sha256_transform" moduleName="sha256_transform" rtlName="e_V_fu_2667_p2" latency="0" BRAM="-1" DSP="-1" FF="0" LUT="39" fileDirectory="D:\Phan_mem\Phan_mem\XilinxVivado\zynq_book\sha_256"&gt;&lt;\/item&gt;
<item  id="603" filename="../../../../../Dell/Documents/HK2_2526/HW_SW/Project_ck/HLS/sha256.cpp" linenumber="45" name="add_ln209_5" contextFuncName="sha256_transform" moduleName="sha256_transform" rtlName="add_ln209_5_fu_2673_p2" latency="0" BRAM="-1" DSP="-1" FF="0" LUT="32" fileDirectory="D:\Phan_mem\Phan_mem\XilinxVivado\zynq_book\sha_256"&gt;&lt;\/item&gt;
<item  id="604" filename="../../../../../Dell/Documents/HK2_2526/HW_SW/Project_ck/HLS/sha256.cpp" linenumber="45" name="a_V" contextFuncName="sha256_transform" moduleName="sha256_transform" rtlName="a_V_fu_2679_p2" latency="0" BRAM="-1" DSP="-1" FF="0" LUT="32" fileDirectory="D:\Phan_mem\Phan_mem\XilinxVivado\zynq_book\sha_256"&gt;&lt;\/item&gt;
<item  id="608" filename="../../../../../Dell/Documents/HK2_2526/HW_SW/Project_ck/HLS/sha256.cpp" linenumber="48" name="add_ln700" contextFuncName="sha256_transform" moduleName="sha256_transform" rtlName="add_ln700_fu_2491_p2" latency="0" BRAM="-1" DSP="-1" FF="0" LUT="39" fileDirectory="D:\Phan_mem\Phan_mem\XilinxVivado\zynq_book\sha_256"&gt;&lt;\/item&gt;
<item  id="609" filename="../../../../../Dell/Documents/HK2_2526/HW_SW/Project_ck/HLS/sha256.cpp" linenumber="48" name="add_ln700_1" contextFuncName="sha256_transform" moduleName="sha256_transform" rtlName="add_ln700_1_fu_2496_p2" latency="0" BRAM="-1" DSP="-1" FF="0" LUT="39" fileDirectory="D:\Phan_mem\Phan_mem\XilinxVivado\zynq_book\sha_256"&gt;&lt;\/item&gt;
<item  id="610" filename="../../../../../Dell/Documents/HK2_2526/HW_SW/Project_ck/HLS/sha256.cpp" linenumber="48" name="add_ln700_2" contextFuncName="sha256_transform" moduleName="sha256_transform" rtlName="add_ln700_2_fu_2501_p2" latency="0" BRAM="-1" DSP="-1" FF="0" LUT="39" fileDirectory="D:\Phan_mem\Phan_mem\XilinxVivado\zynq_book\sha_256"&gt;&lt;\/item&gt;
<item  id="611" filename="../../../../../Dell/Documents/HK2_2526/HW_SW/Project_ck/HLS/sha256.cpp" linenumber="48" name="add_ln700_3" contextFuncName="sha256_transform" moduleName="sha256_transform" rtlName="add_ln700_3_fu_2506_p2" latency="0" BRAM="-1" DSP="-1" FF="0" LUT="39" fileDirectory="D:\Phan_mem\Phan_mem\XilinxVivado\zynq_book\sha_256"&gt;&lt;\/item&gt;
<item  id="612" filename="../../../../../Dell/Documents/HK2_2526/HW_SW/Project_ck/HLS/sha256.cpp" linenumber="49" name="add_ln700_4" contextFuncName="sha256_transform" moduleName="sha256_transform" rtlName="add_ln700_4_fu_2511_p2" latency="0" BRAM="-1" DSP="-1" FF="0" LUT="39" fileDirectory="D:\Phan_mem\Phan_mem\XilinxVivado\zynq_book\sha_256"&gt;&lt;\/item&gt;
<item  id="613" filename="../../../../../Dell/Documents/HK2_2526/HW_SW/Project_ck/HLS/sha256.cpp" linenumber="49" name="add_ln700_5" contextFuncName="sha256_transform" moduleName="sha256_transform" rtlName="add_ln700_5_fu_2516_p2" latency="0" BRAM="-1" DSP="-1" FF="0" LUT="39" fileDirectory="D:\Phan_mem\Phan_mem\XilinxVivado\zynq_book\sha_256"&gt;&lt;\/item&gt;
<item  id="614" filename="../../../../../Dell/Documents/HK2_2526/HW_SW/Project_ck/HLS/sha256.cpp" linenumber="49" name="add_ln700_6" contextFuncName="sha256_transform" moduleName="sha256_transform" rtlName="add_ln700_6_fu_2521_p2" latency="0" BRAM="-1" DSP="-1" FF="0" LUT="39" fileDirectory="D:\Phan_mem\Phan_mem\XilinxVivado\zynq_book\sha_256"&gt;&lt;\/item&gt;
<item  id="615" filename="../../../../../Dell/Documents/HK2_2526/HW_SW/Project_ck/HLS/sha256.cpp" linenumber="49" name="add_ln700_7" contextFuncName="sha256_transform" moduleName="sha256_transform" rtlName="add_ln700_7_fu_2526_p2" latency="0" BRAM="-1" DSP="-1" FF="0" LUT="39" fileDirectory="D:\Phan_mem\Phan_mem\XilinxVivado\zynq_book\sha_256"&gt;&lt;\/item&gt;
&lt;\/annotationInfo&gt;
<annotationInfo>
<item  id="72" filename="../../../../../Dell/Documents/HK2_2526/HW_SW/Project_ck/HLS/sha256.cpp" linenumber="79" name="call_ret_dup" contextFuncName="sha256_core" moduleName="sha256_core" rtlName="grp_sha256_transform_fu_359" latency="1" BRAM="-1" DSP="-1" FF="-1" LUT="-1" fileDirectory="D:\Phan_mem\Phan_mem\XilinxVivado\zynq_book\sha_256"><\/item>
<item  id="81" filename="../../../../../Dell/Documents/HK2_2526/HW_SW/Project_ck/HLS/sha256.cpp" linenumber="73" name="icmp_ln73" contextFuncName="sha256_core" moduleName="sha256_core" rtlName="icmp_ln73_fu_469_p2" latency="0" BRAM="-1" DSP="-1" FF="0" LUT="21" fileDirectory="D:\Phan_mem\Phan_mem\XilinxVivado\zynq_book\sha_256"><\/item>
<item  id="82" filename="../../../../../Dell/Documents/HK2_2526/HW_SW/Project_ck/HLS/sha256.cpp" linenumber="73" name="add_ln73" contextFuncName="sha256_core" moduleName="sha256_core" rtlName="add_ln73_fu_474_p2" latency="0" BRAM="-1" DSP="-1" FF="0" LUT="43" fileDirectory="D:\Phan_mem\Phan_mem\XilinxVivado\zynq_book\sha_256"><\/item>
<item  id="86" filename="../../../../../Dell/Documents/HK2_2526/HW_SW/Project_ck/HLS/sha256.cpp" linenumber="75" name="icmp_ln75" contextFuncName="sha256_core" moduleName="sha256_core" rtlName="icmp_ln75_fu_512_p2" latency="0" BRAM="-1" DSP="-1" FF="0" LUT="11" fileDirectory="D:\Phan_mem\Phan_mem\XilinxVivado\zynq_book\sha_256"><\/item>
<item  id="87" filename="../../../../../Dell/Documents/HK2_2526/HW_SW/Project_ck/HLS/sha256.cpp" linenumber="75" name="select_ln75" contextFuncName="sha256_core" moduleName="sha256_core" rtlName="select_ln75_fu_518_p3" latency="0" BRAM="-1" DSP="-1" FF="0" LUT="5" fileDirectory="D:\Phan_mem\Phan_mem\XilinxVivado\zynq_book\sha_256"><\/item>
<item  id="88" filename="../../../../../Dell/Documents/HK2_2526/HW_SW/Project_ck/HLS/sha256.cpp" linenumber="73" name="select_ln73" contextFuncName="sha256_core" moduleName="sha256_core" rtlName="select_ln73_fu_526_p3" latency="0" BRAM="-1" DSP="-1" FF="0" LUT="32" fileDirectory="D:\Phan_mem\Phan_mem\XilinxVivado\zynq_book\sha_256"><\/item>
<item  id="89" filename="../../../../../Dell/Documents/HK2_2526/HW_SW/Project_ck/HLS/sha256.cpp" linenumber="73" name="select_ln73_1" contextFuncName="sha256_core" moduleName="sha256_core" rtlName="select_ln73_1_fu_534_p3" latency="0" BRAM="-1" DSP="-1" FF="0" LUT="32" fileDirectory="D:\Phan_mem\Phan_mem\XilinxVivado\zynq_book\sha_256"><\/item>
<item  id="90" filename="../../../../../Dell/Documents/HK2_2526/HW_SW/Project_ck/HLS/sha256.cpp" linenumber="73" name="select_ln73_2" contextFuncName="sha256_core" moduleName="sha256_core" rtlName="select_ln73_2_fu_542_p3" latency="0" BRAM="-1" DSP="-1" FF="0" LUT="32" fileDirectory="D:\Phan_mem\Phan_mem\XilinxVivado\zynq_book\sha_256"><\/item>
<item  id="91" filename="../../../../../Dell/Documents/HK2_2526/HW_SW/Project_ck/HLS/sha256.cpp" linenumber="73" name="select_ln73_3" contextFuncName="sha256_core" moduleName="sha256_core" rtlName="select_ln73_3_fu_550_p3" latency="0" BRAM="-1" DSP="-1" FF="0" LUT="32" fileDirectory="D:\Phan_mem\Phan_mem\XilinxVivado\zynq_book\sha_256"><\/item>
<item  id="92" filename="../../../../../Dell/Documents/HK2_2526/HW_SW/Project_ck/HLS/sha256.cpp" linenumber="73" name="select_ln73_4" contextFuncName="sha256_core" moduleName="sha256_core" rtlName="select_ln73_4_fu_558_p3" latency="0" BRAM="-1" DSP="-1" FF="0" LUT="32" fileDirectory="D:\Phan_mem\Phan_mem\XilinxVivado\zynq_book\sha_256"><\/item>
<item  id="93" filename="../../../../../Dell/Documents/HK2_2526/HW_SW/Project_ck/HLS/sha256.cpp" linenumber="73" name="select_ln73_5" contextFuncName="sha256_core" moduleName="sha256_core" rtlName="select_ln73_5_fu_566_p3" latency="0" BRAM="-1" DSP="-1" FF="0" LUT="32" fileDirectory="D:\Phan_mem\Phan_mem\XilinxVivado\zynq_book\sha_256"><\/item>
<item  id="94" filename="../../../../../Dell/Documents/HK2_2526/HW_SW/Project_ck/HLS/sha256.cpp" linenumber="73" name="select_ln73_6" contextFuncName="sha256_core" moduleName="sha256_core" rtlName="select_ln73_6_fu_574_p3" latency="0" BRAM="-1" DSP="-1" FF="0" LUT="32" fileDirectory="D:\Phan_mem\Phan_mem\XilinxVivado\zynq_book\sha_256"><\/item>
<item  id="95" filename="../../../../../Dell/Documents/HK2_2526/HW_SW/Project_ck/HLS/sha256.cpp" linenumber="73" name="select_ln73_7" contextFuncName="sha256_core" moduleName="sha256_core" rtlName="select_ln73_7_fu_582_p3" latency="0" BRAM="-1" DSP="-1" FF="0" LUT="32" fileDirectory="D:\Phan_mem\Phan_mem\XilinxVivado\zynq_book\sha_256"><\/item>
<item  id="101" filename="../../../../../Dell/Documents/HK2_2526/HW_SW/Project_ck/HLS/sha256.cpp" linenumber="77" name="trunc_ln321" contextFuncName="sha256_core" moduleName="sha256_core" rtlName="trunc_ln321_fu_594_p1" latency="0" BRAM="-1" DSP="-1" FF="-1" LUT="-1" fileDirectory="D:\Phan_mem\Phan_mem\XilinxVivado\zynq_book\sha_256"><\/item>
<item  id="153" filename="../../../../../Dell/Documents/HK2_2526/HW_SW/Project_ck/HLS/sha256.cpp" linenumber="75" name="i" contextFuncName="sha256_core" moduleName="sha256_core" rtlName="i_fu_678_p2" latency="0" BRAM="-1" DSP="-1" FF="0" LUT="15" fileDirectory="D:\Phan_mem\Phan_mem\XilinxVivado\zynq_book\sha_256"><\/item>
<item  id="159" filename="../../../../../Dell/Documents/HK2_2526/HW_SW/Project_ck/HLS/sha256.cpp" linenumber="83" name="icmp_ln83" contextFuncName="sha256_core" moduleName="sha256_core" rtlName="icmp_ln83_fu_683_p2" latency="0" BRAM="-1" DSP="-1" FF="0" LUT="11" fileDirectory="D:\Phan_mem\Phan_mem\XilinxVivado\zynq_book\sha_256"><\/item>
<item  id="161" filename="../../../../../Dell/Documents/HK2_2526/HW_SW/Project_ck/HLS/sha256.cpp" linenumber="83" name="i_3" contextFuncName="sha256_core" moduleName="sha256_core" rtlName="i_3_fu_689_p2" latency="0" BRAM="-1" DSP="-1" FF="0" LUT="13" fileDirectory="D:\Phan_mem\Phan_mem\XilinxVivado\zynq_book\sha_256"><\/item>
<item  id="167" filename="../../../../../Dell/Documents/HK2_2526/HW_SW/Project_ck/HLS/sha256.cpp" linenumber="86" name="trunc_ln78" contextFuncName="sha256_core" moduleName="sha256_core" rtlName="out_word_data_V_fu_699_p9" latency="0" BRAM="-1" DSP="-1" FF="-1" LUT="-1" fileDirectory="D:\Phan_mem\Phan_mem\XilinxVivado\zynq_book\sha_256"><\/item>
<item  id="168" filename="../../../../../Dell/Documents/HK2_2526/HW_SW/Project_ck/HLS/sha256.cpp" linenumber="86" name="out_word_data_V" contextFuncName="sha256_core" moduleName="sha256_core" rtlName="sha256_core_mux_8dEe_U37" latency="0" BRAM="-1" DSP="-1" FF="-1" LUT="-1" fileDirectory="D:\Phan_mem\Phan_mem\XilinxVivado\zynq_book\sha_256"><\/item>
<item  id="169" filename="../../../../../Dell/Documents/HK2_2526/HW_SW/Project_ck/HLS/sha256.cpp" linenumber="87" name="out_word_last_V" contextFuncName="sha256_core" moduleName="sha256_core" rtlName="out_word_last_V_fu_713_p2" latency="0" BRAM="-1" DSP="-1" FF="0" LUT="9" fileDirectory="D:\Phan_mem\Phan_mem\XilinxVivado\zynq_book\sha_256"><\/item>
<\/annotationInfo>
</annotationInfo>
